adi/ADIDatCAPI_mex.h
adi/ADIDatIOWin.dll
adi/ADIDatIOWin.lib
adi/ADIDatIOWin64.dll
adi/ADIDatIOWin64.lib
adi/__init__.py
adi/_adi_cffi.c
adi/_adi_cffi.cp310-win_amd64.pyd
adi/_adi_cffi.cp311-win_amd64.pyd
adi/_adi_cffi.cp312-win_amd64.pyd
adi/_adi_cffi.cp313-win_amd64.pyd
adi/_adi_cffi.cp36-win_amd64.pyd
adi/_adi_cffi.cp37-win_amd64.pyd
adi/_adi_cffi.cp38-win_amd64.pyd
adi/_adi_cffi.cp39-win_amd64.pyd
adi/_adi_cffi2.c
adi/_adi_cffi2.cp38-win32.pyd
adi/_adi_cffi2.cp39-win32.pyd
adi/cffi_build.py
adi/cffi_build_win32.py
adi/cffi_build_win32.py.bak
adi/read.py
adi_reader-0.0.13.dist-info/LICENSE
adi_reader-0.0.13.dist-info/METADATA
adi_reader-0.0.13.dist-info/WHEEL
adi_reader-0.0.13.dist-info/top_level.txt
adi_reader-0.0.13.dist-info/RECORD
