Metadata-Version: 2.1
Name: adi-reader
Version: 0.0.13
Summary: Reading LabChart recorded data
Home-page: https://github.com/JimHokanson/adinstruments_sdk_python/
Author: Jim Hokanson
Author-email: jim.hokanson@gmail.com
Classifier: Programming Language :: Python :: 3
Classifier: License :: OSI Approved :: MIT License
Classifier: Operating System :: Microsoft :: Windows
Requires-Python: >= 3.6, <= 3.13
License-File: LICENSE
Requires-Dist: numpy
Requires-Dist: cffi
